JLTomorrow/__init__.py
JLTomorrow/_version.py
JLTomorrow/labextension/package.json
JLTomorrow/labextension/static/534.78d0766432810af83c50.js
JLTomorrow/labextension/static/568.5bfab1058a5c27f64be2.js
JLTomorrow/labextension/static/remoteEntry.f68905a04e8d269eb06d.js
JLTomorrow/labextension/static/style.js
JLTomorrow/labextension/themes/JLTomorrow/index.css
JLTomorrow/labextension/themes/JLTomorrow/index.js
JLTomorrow-0.1.0.data/data/share/jupyter/labextensions/JLTomorrow/install.json
JLTomorrow-0.1.0.data/data/share/jupyter/labextensions/JLTomorrow/package.json
JLTomorrow-0.1.0.data/data/share/jupyter/labextensions/JLTomorrow/static/534.78d0766432810af83c50.js
JLTomorrow-0.1.0.data/data/share/jupyter/labextensions/JLTomorrow/static/568.5bfab1058a5c27f64be2.js
JLTomorrow-0.1.0.data/data/share/jupyter/labextensions/JLTomorrow/static/remoteEntry.f68905a04e8d269eb06d.js
JLTomorrow-0.1.0.data/data/share/jupyter/labextensions/JLTomorrow/static/style.js
JLTomorrow-0.1.0.data/data/share/jupyter/labextensions/JLTomorrow/themes/JLTomorrow/index.css
JLTomorrow-0.1.0.data/data/share/jupyter/labextensions/JLTomorrow/themes/JLTomorrow/index.js
JLTomorrow-0.1.0.dist-info/LICENSE
JLTomorrow-0.1.0.dist-info/METADATA
JLTomorrow-0.1.0.dist-info/WHEEL
JLTomorrow-0.1.0.dist-info/top_level.txt
JLTomorrow-0.1.0.dist-info/RECORD
